[
  {
    "id": "cv_001",
    "thai": "เพราะ...จึง",
    "roman": "phró ... jueng",
    "en": "because ... therefore",
    "type": "causal",
    "exampleTH": "เพราะฝนตกหนัก จึงรถติดมาก",
    "exampleEN": "Because it rained heavily, the traffic was severe.",
    "tts": "เพราะฝนตกหนัก จึงรถติดมาก",
    "clozeTH": "___ฝนตกหนัก จึงรถติดมาก"
  },
  {
    "id": "cv_002",
    "thai": "เนื่องจาก...จึง",
    "roman": "nueang-jàak ... jueng",
    "en": "due to ... therefore",
    "type": "causal",
    "exampleTH": "เนื่องจากระบบล่ม จึงต้องเลื่อนการประชุม",
    "exampleEN": "Due to a system outage, the meeting had to be postponed.",
    "tts": "เนื่องจากระบบล่ม จึงต้องเลื่อนการประชุม",
    "clozeTH": "___ระบบล่ม จึงต้องเลื่อนการประชุม"
  },
  {
    "id": "cv_003",
    "thai": "แม้ว่า...แต่",
    "roman": "mǽæ wâa ... tɛ̀ɛ",
    "en": "although ... but",
    "type": "concession",
    "exampleTH": "แม้ว่าอากาศร้อน แต่เขายังออกไปวิ่ง",
    "exampleEN": "Although it's hot, he still goes running.",
    "tts": "แม้ว่าอากาศร้อน แต่เขายังออกไปวิ่ง",
    "clozeTH": "___อากาศร้อน แต่เขายังออกไปวิ่ง"
  },
  {
    "id": "cv_004",
    "thai": "ถึงแม้ว่า...ก็",
    "roman": "thʉ̌ng-mǽæ-wâa ... kɔ̂",
    "en": "even though ... still",
    "type": "concession",
    "exampleTH": "ถึงแม้ว่างานหนัก เขาก็ทำสำเร็จ",
    "exampleEN": "Even though the work was heavy, he still succeeded.",
    "tts": "ถึงแม้ว่างานหนัก เขาก็ทำสำเร็จ",
    "clozeTH": "___งานหนัก เขาก็ทำสำเร็จ"
  },
  {
    "id": "cv_005",
    "thai": "ถ้า...ก็",
    "roman": "thâa ... kɔ̂",
    "en": "if ... then",
    "type": "condition",
    "exampleTH": "ถ้าฝนไม่ตก เราก็ไปปีนเขา",
    "exampleEN": "If it doesn't rain, we'll go hiking.",
    "tts": "ถ้าฝนไม่ตก เราก็ไปปีนเขา",
    "clozeTH": "___ฝนไม่ตก เราก็ไปปีนเขา"
  },
  {
    "id": "cv_006",
    "thai": "หาก...จะ",
    "roman": "hàak ... jà",
    "en": "should ... will",
    "type": "condition",
    "exampleTH": "หากคุณพร้อม เราจะเริ่มทันที",
    "exampleEN": "If you're ready, we will start immediately.",
    "tts": "หากคุณพร้อม เราจะเริ่มทันที",
    "clozeTH": "___คุณพร้อม เราจะเริ่มทันที"
  },
  {
    "id": "cv_007",
    "thai": "เมื่อ...ก็",
    "roman": "mʉ̂a ... kɔ̂",
    "en": "when ... then",
    "type": "temporal",
    "exampleTH": "เมื่อถึงเวลา ก็ออกเดินทาง",
    "exampleEN": "When it's time, then depart.",
    "tts": "เมื่อถึงเวลา ก็ออกเดินทาง",
    "clozeTH": "___ถึงเวลา ก็ออกเดินทาง"
  },
  {
    "id": "cv_008",
    "thai": "เพื่อที่จะ...",
    "roman": "phʉ̂a-thîi-jà ...",
    "en": "in order to ...",
    "type": "purpose",
    "exampleTH": "เพื่อที่จะประหยัดงบ เราจึงใช้ซอฟต์แวร์โอเพนซอร์ส",
    "exampleEN": "In order to save the budget, we used open-source software.",
    "tts": "เพื่อที่จะประหยัดงบ เราจึงใช้ซอฟต์แวร์โอเพนซอร์ส",
    "clozeTH": "___ประหยัดงบ เราจึงใช้ซอฟต์แวร์โอเพนซอร์ส"
  },
  {
    "id": "cv_009",
    "thai": "ไม่เพียงแต่...แต่ยัง...",
    "roman": "mâi phiang tɛ̀ɛ ... tɛ̀ɛ yang ...",
    "en": "not only ... but also ...",
    "type": "additive",
    "exampleTH": "ไม่เพียงแต่เร็ว แต่ยังปลอดภัย",
    "exampleEN": "Not only fast, but also safe.",
    "tts": "ไม่เพียงแต่เร็ว แต่ยังปลอดภัย",
    "clozeTH": "___เร็ว แต่ยังปลอดภัย"
  },
  {
    "id": "cv_010",
    "thai": "นอกจาก...ก็ยัง...",
    "roman": "nâawk-jàak ... kɔ̂ yang ...",
    "en": "besides ... also ...",
    "type": "additive",
    "exampleTH": "นอกจากเรียน ก็ยังทำงานพาร์ทไทม์",
    "exampleEN": "Besides studying, she also works part-time.",
    "tts": "นอกจากเรียน ก็ยังทำงานพาร์ทไทม์",
    "clozeTH": "___เรียน ก็ยังทำงานพาร์ทไทม์"
  },
  {
    "id": "cv_011",
    "thai": "ยิ่ง...ยิ่ง...",
    "roman": "yîng ... yîng ...",
    "en": "the more ... the more ...",
    "type": "correlative",
    "exampleTH": "ยิ่งฝึกมาก ยิ่งเก่งเร็ว",
    "exampleEN": "The more you practice, the faster you improve.",
    "tts": "ยิ่งฝึกมาก ยิ่งเก่งเร็ว",
    "clozeTH": "___ฝึกมาก ___เก่งเร็ว"
  },
  {
    "id": "cv_012",
    "thai": "แทนที่จะ...",
    "roman": "thææn-thîi-jà ...",
    "en": "instead of ...",
    "type": "contrast",
    "exampleTH": "แทนที่จะผัดวันประกันพรุ่ง เขาลงมือทำทันที",
    "exampleEN": "Instead of procrastinating, he acted immediately.",
    "tts": "แทนที่จะผัดวันประกันพรุ่ง เขาลงมือทำทันที",
    "clozeTH": "___ผัดวันประกันพรุ่ง เขาลงมือทำทันที"
  }
]
